{"content":{"title":"নজরের হেফাজত সম্পর্কে কুরআনের আয়াত","subtitle":"তিনিই চক্ষুর অপব্যবহার এবং অন্তরের গোপন বস্তু সম্পর্কেও অবগত","image":"https://raw.githubusercontent.com/qwer87asdf/lI0IlolI-km/refs/heads/master/notification/image/random/mahfil-app.png","body":"<p>পবিত্র কুরআনে আল্লাহ তায়ালা বলেন:</p><p class=\"quran\">یَعۡلَمُ خَآئِنَۃَ الۡاَعۡیُنِ وَ مَا تُخۡفِی الصُّدُوۡرُ</p><p>অর্থ: তিনিই চক্ষুর অপব্যবহার এবং অন্তরের গোপন বস্তু সম্পর্কেও অবগত [সূরা গাফির, আয়াত: ১৯]</p><p>আফসোস, আমাদের মধ্যে বেশিরভাগ মানুষ খাবার ত্যাগ করেই সিয়ামের হক আদায় হয়ে যাবে বলে মনে করি। অথচ আল্লাহ সুবহানাহু তায়ালা পবিত্র কুরআনে এবং হাদিসের মাদ্ধমে আমাদের বারংবার নজরের যেনা থেকে দূরে থাকতে বলেছেন। ইফতারের এই পবিত্র এবং মহিমান্বিত সময়ে টাইমপাস নামক ধোঁকায় পরে ফেইসবুক, ইউটিউব, টিকটকে এমন সব অযাচিত বিষয় উপভোগ করছি যা আমাদের সিয়াম থাকা অবস্থায় বার বার যেনার মতো ভয়ঙ্কর গুনাহে জড়িয়ে ফেলছে। মনে রাখুন, আল্লাহ আপনাকে দেখছে।</p><p>জানি স্মার্টফোন হাতে থাকায় অনেকেই ইফতারির সময় কুরআন তিলাওয়াত বা বিভিন্ন কারণে অনলাইনে সময় কাটাই। তবে কতোই না উত্তম হতো যদি এই কুরআন তিলাওয়াত শুনতে গিয়ে বা ভিডিও দেখতে গিয়ে মহান রব নারাজ হন অথবা চোখের যেনা হয় এমন কিছুই দেখতে হতো না, সুবহানাল্লাহ!</p><p>আলহামদুলিল্লাহ, প্রতিটি দ্বীনপিপাসু মানুষের জন্য Mahfil অ্যাপ তেমনি একটা প্লাটফর্ম যেখানে যতক্ষণ থাকবেন শুধু হালাল এবং শরিয়া সম্মত বিষয় উপভোগ করবেন ইনশাআল্লাহ।</p><p>মাহফিল অ্যাপটি ডাউনলোড করতে পারেন এখান থেকে: <a href=\"https://kahf.to/MahfilQR\" data-as-button=\"false\">https://kahf.to/MahfilQR</a></p><p>আপনার সামান্য একটু সচেতনতাই পারে আপনার পরিবার এবং বন্ধুবান্ধব সকলকে ইউটিউব/ফেইসবুক নামক অন্ধকার গুহা থেকে ফিরিয়ে এনে এই আলোর পথ দেখাতে, বি&#039;কুদরাতিল্লাহ!</p><p>আল্লাহ আমাদের সকলের পথচলা সহজ করুন, আমীন ।</p><p>জাজাকাল্লাহ খায়ের</p>"},"reference":[],"footer_button":{"hint":"মাহফিল সহ কাহফ পরিবারের সকল হালাল অ্যাপ সম্পর্কে জানতে ভিজিট করুন","text":"কাহফের প্লে স্টোরে যান","link":"https://play.google.com/store/apps/developer?id=Kahf"}}